nam/__init__.py
nam/model.py
nam/train.py
nam/visualization.py
pytorch_nam-0.1.0.dist-info/METADATA
pytorch_nam-0.1.0.dist-info/WHEEL
pytorch_nam-0.1.0.dist-info/licenses/LICENSE.md
pytorch_nam-0.1.0.dist-info/RECORD
