Metadata-Version: 2.4
Name: pytorch-nam
Version: 0.1.0
Summary: Neural Additive Models (NAM) library for interpretable machine learning with shape function visualization
Project-URL: Homepage, https://github.com/flix59/nam_explorer
Project-URL: Repository, https://github.com/flix59/nam_explorer
Project-URL: Issues, https://github.com/flix59/nam_explorer/issues
Author-email: Felix <felix@aipieper.de>
License: 
License-File: LICENSE.md
Keywords: explainable ai,interpretable ml,machine learning,neural additive models,pytorch
Classifier: Development Status :: 3 - Alpha
Classifier: Intended Audience :: Science/Research
Classifier: License :: OSI Approved :: MIT License
Classifier: Programming Language :: Python :: 3
Classifier: Programming Language :: Python :: 3.9
Classifier: Programming Language :: Python :: 3.10
Classifier: Programming Language :: Python :: 3.11
Classifier: Programming Language :: Python :: 3.12
Classifier: Programming Language :: Python :: 3.13
Classifier: Topic :: Scientific/Engineering :: Artificial Intelligence
Requires-Python: >=3.9
Requires-Dist: matplotlib>=3.7.0
Requires-Dist: numpy>=1.24.0
Requires-Dist: torch>=2.0.0
Provides-Extra: all
Requires-Dist: gradio>=5.0.0; extra == 'all'
Requires-Dist: pandas>=2.0.0; extra == 'all'
Requires-Dist: plotly>=5.0.0; extra == 'all'
Requires-Dist: scikit-learn>=1.3.0; extra == 'all'
Provides-Extra: data
Requires-Dist: pandas>=2.0.0; extra == 'data'
Requires-Dist: scikit-learn>=1.3.0; extra == 'data'
Provides-Extra: dev
Requires-Dist: black>=23.0.0; extra == 'dev'
Requires-Dist: pytest>=7.0.0; extra == 'dev'
Requires-Dist: ruff>=0.1.0; extra == 'dev'
Provides-Extra: viz
Requires-Dist: gradio>=5.0.0; extra == 'viz'
Requires-Dist: plotly>=5.0.0; extra == 'viz'
